odoo/addons/artiga/__init__.py
odoo/addons/artiga/__manifest__.py
odoo/addons/artiga/static/src/xml/pos.xml
odoo_addon_artiga-16.0.1.0.0.1.dist-info/METADATA
odoo_addon_artiga-16.0.1.0.0.1.dist-info/WHEEL
odoo_addon_artiga-16.0.1.0.0.1.dist-info/top_level.txt
odoo_addon_artiga-16.0.1.0.0.1.dist-info/RECORD
