Metadata-Version: 2.1
Name: odoo-addon-artiga
Version: 16.0.1.0.0.1
Requires-Python: >=3.10
Requires-Dist: odoo-addon-l10n_es_pos>=16.0dev,<16.1dev
Requires-Dist: odoo>=16.0a,<16.1dev
Summary: Odoo customizations for Artiga.
Home-page: https://coopdevs.org
License: AGPL-3
Author: Coopdevs Treball SCCL
Classifier: Programming Language :: Python
Classifier: Framework :: Odoo
Classifier: Framework :: Odoo :: 16.0
Classifier: License :: OSI Approved :: GNU Affero General Public License v3
